[
  {
    "type": "Occurrence",
    "language": "fr",
    "license": "CC-BY-4.0",
    "rightsHolder": "Niamoto - Nouvelle-Calédonie",
    "datasetName": "Niamoto Export - Nouvelle-Calédonie Flore",
    "basisOfRecord": "HumanObservation",
    "occurrenceID": "niaocc_58777",
    "individualCount": "1",
    "occurrenceStatus": "present",
    "eventID": "niaevt_58777",
    "month": 5,
    "country": "New Caledonia",
    "countryCode": "NC",
    "minimumElevationInMeters": 600.0,
    "maximumElevationInMeters": 600.0,
    "decimalLatitude": -20.952782313029,
    "decimalLongitude": 164.914333470662,
    "geodeticDatum": "WGS84",
    "identificationID": "niaid_unknown_0",
    "taxonID": 720,
    "scientificName": "Dendrocnide peltata (Blume) Miq.",
    "kingdom": "Plantae",
    "family": "Urticaceae",
    "genus": "Dendrocnide",
    "specificEpithet": "peltata",
    "taxonRank": "species",
    "scientificNameAuthorship": "Dendrocnide peltata (Blume) Miq.",
    "habitat": "Holdridge life zone: Zone 2.0; Annual rainfall: 2260.0mm; Substrate: non-ultramafic; Habitat: non-forest"
  },
  {
    "type": "Occurrence",
    "language": "fr",
    "license": "CC-BY-4.0",
    "rightsHolder": "Niamoto - Nouvelle-Calédonie",
    "datasetName": "Niamoto Export - Nouvelle-Calédonie Flore",
    "basisOfRecord": "HumanObservation",
    "occurrenceID": "niaocc_58775",
    "individualCount": "1",
    "occurrenceStatus": "present",
    "eventID": "niaevt_58775",
    "month": 1,
    "country": "New Caledonia",
    "countryCode": "NC",
    "minimumElevationInMeters": 114.0,
    "maximumElevationInMeters": 114.0,
    "decimalLatitude": -20.653738339742,
    "decimalLongitude": 164.475244998932,
    "geodeticDatum": "WGS84",
    "identificationID": "niaid_unknown_1",
    "taxonID": 720,
    "scientificName": "Dendrocnide peltata (Blume) Miq.",
    "kingdom": "Plantae",
    "family": "Urticaceae",
    "genus": "Dendrocnide",
    "specificEpithet": "peltata",
    "taxonRank": "species",
    "scientificNameAuthorship": "Dendrocnide peltata (Blume) Miq.",
    "habitat": "Holdridge life zone: Zone 2.0; Annual rainfall: 1170.0mm; Substrate: non-ultramafic; Habitat: non-forest"
  },
  {
    "type": "Occurrence",
    "language": "fr",
    "license": "CC-BY-4.0",
    "rightsHolder": "Niamoto - Nouvelle-Calédonie",
    "datasetName": "Niamoto Export - Nouvelle-Calédonie Flore",
    "basisOfRecord": "HumanObservation",
    "occurrenceID": "niaocc_58778",
    "individualCount": "1",
    "occurrenceStatus": "present",
    "eventID": "niaevt_58778",
    "month": 9,
    "country": "New Caledonia",
    "countryCode": "NC",
    "minimumElevationInMeters": 769.0,
    "maximumElevationInMeters": 769.0,
    "decimalLatitude": -20.95063591,
    "decimalLongitude": 164.92033386,
    "geodeticDatum": "WGS84",
    "identificationID": "niaid_unknown_2",
    "taxonID": 720,
    "scientificName": "Dendrocnide peltata (Blume) Miq.",
    "kingdom": "Plantae",
    "family": "Urticaceae",
    "genus": "Dendrocnide",
    "specificEpithet": "peltata",
    "taxonRank": "species",
    "scientificNameAuthorship": "Dendrocnide peltata (Blume) Miq.",
    "dynamicProperties": "{\"diameterAtBreastHeight\": {\"value\": 23.6, \"unit\": \"cm\"}}",
    "habitat": "Holdridge life zone: Zone 3.0; Annual rainfall: 2260.0mm; Substrate: non-ultramafic; Habitat: non-forest"
  },
  {
    "type": "Occurrence",
    "language": "fr",
    "license": "CC-BY-4.0",
    "rightsHolder": "Niamoto - Nouvelle-Calédonie",
    "datasetName": "Niamoto Export - Nouvelle-Calédonie Flore",
    "basisOfRecord": "HumanObservation",
    "occurrenceID": "niaocc_58780",
    "individualCount": "1",
    "occurrenceStatus": "present",
    "eventID": "niaevt_58780",
    "month": 6,
    "country": "New Caledonia",
    "countryCode": "NC",
    "minimumElevationInMeters": 95.0,
    "maximumElevationInMeters": 95.0,
    "decimalLatitude": -22.6069583,
    "decimalLongitude": 167.4730564,
    "geodeticDatum": "WGS84",
    "identificationID": "niaid_unknown_3",
    "taxonID": 720,
    "scientificName": "Dendrocnide peltata (Blume) Miq.",
    "kingdom": "Plantae",
    "family": "Urticaceae",
    "genus": "Dendrocnide",
    "specificEpithet": "peltata",
    "taxonRank": "species",
    "scientificNameAuthorship": "Dendrocnide peltata (Blume) Miq.",
    "habitat": "Holdridge life zone: Zone 2.0; Annual rainfall: 1280.0mm; Substrate: ultramafic; Habitat: non-forest"
  },
  {
    "type": "Occurrence",
    "language": "fr",
    "license": "CC-BY-4.0",
    "rightsHolder": "Niamoto - Nouvelle-Calédonie",
    "datasetName": "Niamoto Export - Nouvelle-Calédonie Flore",
    "basisOfRecord": "HumanObservation",
    "occurrenceID": "niaocc_58779",
    "individualCount": "1",
    "occurrenceStatus": "present",
    "eventID": "niaevt_58779",
    "month": 11,
    "country": "New Caledonia",
    "countryCode": "NC",
    "minimumElevationInMeters": 296.0,
    "maximumElevationInMeters": 296.0,
    "decimalLatitude": -21.222879521052,
    "decimalLongitude": 165.43393386205,
    "geodeticDatum": "WGS84",
    "identificationID": "niaid_unknown_4",
    "taxonID": 720,
    "scientificName": "Dendrocnide peltata (Blume) Miq.",
    "kingdom": "Plantae",
    "family": "Urticaceae",
    "genus": "Dendrocnide",
    "specificEpithet": "peltata",
    "taxonRank": "species",
    "scientificNameAuthorship": "Dendrocnide peltata (Blume) Miq.",
    "habitat": "Holdridge life zone: Zone 2.0; Annual rainfall: 1880.0mm; Substrate: non-ultramafic; Habitat: non-forest"
  },
  {
    "type": "Occurrence",
    "language": "fr",
    "license": "CC-BY-4.0",
    "rightsHolder": "Niamoto - Nouvelle-Calédonie",
    "datasetName": "Niamoto Export - Nouvelle-Calédonie Flore",
    "basisOfRecord": "HumanObservation",
    "occurrenceID": "niaocc_58774",
    "individualCount": "1",
    "occurrenceStatus": "present",
    "eventID": "niaevt_58774",
    "country": "New Caledonia",
    "countryCode": "NC",
    "minimumElevationInMeters": 119.0,
    "maximumElevationInMeters": 119.0,
    "decimalLatitude": -20.3165155649185,
    "decimalLongitude": 164.423781512305,
    "geodeticDatum": "WGS84",
    "identificationID": "niaid_unknown_5",
    "taxonID": 720,
    "scientificName": "Dendrocnide peltata (Blume) Miq.",
    "kingdom": "Plantae",
    "family": "Urticaceae",
    "genus": "Dendrocnide",
    "specificEpithet": "peltata",
    "taxonRank": "species",
    "scientificNameAuthorship": "Dendrocnide peltata (Blume) Miq.",
    "habitat": "Holdridge life zone: Zone 2.0; Annual rainfall: 1760.0mm; Substrate: non-ultramafic; Habitat: non-forest"
  },
  {
    "type": "Occurrence",
    "language": "fr",
    "license": "CC-BY-4.0",
    "rightsHolder": "Niamoto - Nouvelle-Calédonie",
    "datasetName": "Niamoto Export - Nouvelle-Calédonie Flore",
    "basisOfRecord": "HumanObservation",
    "occurrenceID": "niaocc_58776",
    "individualCount": "1",
    "occurrenceStatus": "present",
    "eventID": "niaevt_58776",
    "country": "New Caledonia",
    "countryCode": "NC",
    "minimumElevationInMeters": 256.0,
    "maximumElevationInMeters": 256.0,
    "decimalLatitude": -20.998831987381,
    "decimalLongitude": 164.904880039394,
    "geodeticDatum": "WGS84",
    "identificationID": "niaid_unknown_6",
    "taxonID": 720,
    "scientificName": "Dendrocnide peltata (Blume) Miq.",
    "kingdom": "Plantae",
    "family": "Urticaceae",
    "genus": "Dendrocnide",
    "specificEpithet": "peltata",
    "taxonRank": "species",
    "scientificNameAuthorship": "Dendrocnide peltata (Blume) Miq.",
    "habitat": "Holdridge life zone: Zone 2.0; Annual rainfall: 1360.0mm; Substrate: non-ultramafic; Habitat: non-forest"
  },
  {
    "type": "Occurrence",
    "language": "fr",
    "license": "CC-BY-4.0",
    "rightsHolder": "Niamoto - Nouvelle-Calédonie",
    "datasetName": "Niamoto Export - Nouvelle-Calédonie Flore",
    "basisOfRecord": "HumanObservation",
    "occurrenceID": "niaocc_58781",
    "individualCount": "1",
    "occurrenceStatus": "present",
    "eventID": "niaevt_58781",
    "month": 6,
    "country": "New Caledonia",
    "countryCode": "NC",
    "geodeticDatum": "WGS84",
    "identificationID": "niaid_unknown_7",
    "taxonID": 720,
    "scientificName": "Dendrocnide peltata (Blume) Miq.",
    "kingdom": "Plantae",
    "family": "Urticaceae",
    "genus": "Dendrocnide",
    "specificEpithet": "peltata",
    "taxonRank": "species",
    "scientificNameAuthorship": "Dendrocnide peltata (Blume) Miq.",
    "habitat": "Substrate: non-ultramafic; Habitat: non-forest"
  }
]